sqlitecollections/__init__.py
sqlitecollections/base.py
sqlitecollections/dict.py
sqlitecollections/factory.py
sqlitecollections/list.py
sqlitecollections/logger.py
sqlitecollections/py.typed
sqlitecollections/set.py
sqlitecollections-1.2.0.dist-info/LICENSE
sqlitecollections-1.2.0.dist-info/METADATA
sqlitecollections-1.2.0.dist-info/WHEEL
sqlitecollections-1.2.0.dist-info/top_level.txt
sqlitecollections-1.2.0.dist-info/RECORD
